mlcore/__init__.py
mymlcore-1.1.2.dist-info/METADATA
mymlcore-1.1.2.dist-info/WHEEL
mymlcore-1.1.2.dist-info/top_level.txt
mymlcore-1.1.2.dist-info/RECORD
