Metadata-Version: 2.1
Name: mymlcore
Version: 1.1.2
Summary: A high-performance, extensible machine learning library for Python. fastmlcore provides a rich suite of algorithms, preprocessing tools, metrics, and utilities for rapid prototyping and production-grade ML workflows. Designed for clarity, speed, and flexibility, it empowers researchers, engineers, and data scientists to build, evaluate, and deploy models with ease.
Home-page: https://github.com/arnxv-coder/mymlcore
Author: Arnav Barway AKA arnxv
Author-email: me@arnxv.is-a.dev.com
Classifier: Programming Language :: Python :: 3
Classifier: License :: OSI Approved :: MIT License
Classifier: Operating System :: OS Independent
Classifier: Intended Audience :: Developers
Classifier: Topic :: Scientific/Engineering :: Artificial Intelligence
Requires-Python: >=3.7
Requires-Dist: numpy
